cioyu_math/__init__.py
cioyu_math/乘法表.py
cioyu_math/数组排序.py
cioyu_math-0.2.2.dist-info/METADATA
cioyu_math-0.2.2.dist-info/WHEEL
cioyu_math-0.2.2.dist-info/top_level.txt
cioyu_math-0.2.2.dist-info/RECORD
