Metadata-Version: 2.4
Name: cioyu_math
Version: 0.2.2
Summary: 一个新手写的包
Author: 雷锦华
Classifier: Programming Language :: Python :: 3
Classifier: License :: OSI Approved :: MIT License
Classifier: Operating System :: OS Independent
Requires-Python: >=3.8
